LICENSE
MANIFEST.in
README.md
setup.py
pySpade/DEobs.py
pySpade/DEobsboot.py
pySpade/DErand.py
pySpade/FDRest.py
pySpade/__init__.py
pySpade/__main__.py
pySpade/explevel.py
pySpade/fc.py
pySpade/global.py
pySpade/local.py
pySpade/manhattan.py
pySpade/parsers.py
pySpade/plot_annotation.txt
pySpade/process.py
pySpade/utils.py
pySpade.egg-info/PKG-INFO
pySpade.egg-info/SOURCES.txt
pySpade.egg-info/dependency_links.txt
pySpade.egg-info/entry_points.txt
pySpade.egg-info/top_level.txt