Metadata-Version: 2.1
Name: pySpade
Version: 0.1.6
Summary: Single cell Perturbations - Analysis of Differential gene Expression
Home-page: https://github.com/Hon-lab/pySpade
Author: Yihan Wang
Author-email: Yihan.Wang@UTSouthwestern.edu
License: UNKNOWN
Platform: UNKNOWN
Classifier: Programming Language :: Python :: 3
Classifier: License :: OSI Approved :: MIT License
Classifier: Operating System :: OS Independent
Requires-Python: >=3.7
License-File: LICENSE
